{
  "notes": [
    {
      "id": 1,
      "title": "Note 1",
      "content": "Lorem ipsum dolor sit amet, consectetur adipiscing elit.",
      "created_date": "2021-12-31T15:00:00.000Z",
      "updated_date": "2022-01-01T14:09:57.437Z",
      "tags": [
        "tag4",
        "tag4",
        "tag3",
        "tag3"
      ]
    },
    {
      "id": 2,
      "title": "Note 2",
      "content": "Lorem ipsum dolor sit amet, consectetur adipiscing elit.",
      "created_date": "2022-01-01T15:00:00.000Z",
      "updated_date": "2022-01-02T05:00:32.071Z",
      "tags": [
        "tag4",
        "tag3",
        "tag5"
      ]
    },
    {
      "id": 3,
      "title": "Note 3",
      "content": "Lorem ipsum dolor sit amet, consectetur adipiscing elit.",
      "created_date": "2022-01-02T15:00:00.000Z",
      "updated_date": "2022-01-03T05:08:19.157Z",
      "tags": [
        "tag2",
        "tag1",
        "tag4"
      ]
    },
    {
      "id": 4,
      "title": "Note 4",
      "content": "Lorem ipsum dolor sit amet, consectetur adipiscing elit.",
      "created_date": "2022-01-03T15:00:00.000Z",
      "updated_date": "2022-01-03T23:24:29.446Z",
      "tags": [
        "tag2",
        "tag2",
        "tag1",
        "tag5"
      ]
    },
    {
      "id": 5,
      "title": "Note 5",
      "content": "Lorem ipsum dolor sit amet, consectetur adipiscing elit.",
      "created_date": "2022-01-04T15:00:00.000Z",
      "updated_date": "2022-01-05T10:16:14.532Z",
      "tags": [
        "tag2",
        "tag2",
        "tag2"
      ]
    },
    {
      "id": 6,
      "title": "Note 6",
      "content": "Lorem ipsum dolor sit amet, consectetur adipiscing elit.",
      "created_date": "2022-01-05T15:00:00.000Z",
      "updated_date": "2022-01-05T20:02:17.104Z",
      "tags": [
        "tag2",
        "tag2"
      ]
    },
    {
      "id": 7,
      "title": "Note 7",
      "content": "Lorem ipsum dolor sit amet, consectetur adipiscing elit.",
      "created_date": "2022-01-06T15:00:00.000Z",
      "updated_date": "2022-01-07T06:00:05.209Z",
      "tags": []
    },
    {
      "id": 8,
      "title": "Note 8",
      "content": "Lorem ipsum dolor sit amet, consectetur adipiscing elit.",
      "created_date": "2022-01-07T15:00:00.000Z",
      "updated_date": "2022-01-07T17:30:36.753Z",
      "tags": []
    },
    {
      "id": 9,
      "title": "Note 9",
      "content": "Lorem ipsum dolor sit amet, consectetur adipiscing elit.",
      "created_date": "2022-01-08T15:00:00.000Z",
      "updated_date": "2022-01-09T06:31:54.696Z",
      "tags": [
        "tag5",
        "tag1",
        "tag2"
      ]
    },
    {
      "id": 10,
      "title": "Note 10",
      "content": "Lorem ipsum dolor sit amet, consectetur adipiscing elit.",
      "created_date": "2022-01-09T15:00:00.000Z",
      "updated_date": "2022-01-09T19:49:41.118Z",
      "tags": [
        "tag2",
        "tag1"
      ]
    },
    {
      "id": 11,
      "title": "Note 11",
      "content": "Lorem ipsum dolor sit amet, consectetur adipiscing elit.",
      "created_date": "2022-01-10T15:00:00.000Z",
      "updated_date": "2022-01-11T02:39:29.065Z",
      "tags": [
        "tag5",
        "tag5"
      ]
    },
    {
      "id": 12,
      "title": "Note 12",
      "content": "Lorem ipsum dolor sit amet, consectetur adipiscing elit.",
      "created_date": "2022-01-11T15:00:00.000Z",
      "updated_date": "2022-01-12T14:16:16.196Z",
      "tags": [
        "tag1",
        "tag4",
        "tag1",
        "tag1"
      ]
    },
    {
      "id": 13,
      "title": "Note 13",
      "content": "Lorem ipsum dolor sit amet, consectetur adipiscing elit.",
      "created_date": "2022-01-12T15:00:00.000Z",
      "updated_date": "2022-01-12T19:24:10.512Z",
      "tags": [
        "tag2",
        "tag4",
        "tag4"
      ]
    },
    {
      "id": 14,
      "title": "Note 14",
      "content": "Lorem ipsum dolor sit amet, consectetur adipiscing elit.",
      "created_date": "2022-01-13T15:00:00.000Z",
      "updated_date": "2022-01-13T19:45:33.945Z",
      "tags": [
        "tag4"
      ]
    },
    {
      "id": 15,
      "title": "Note 15",
      "content": "Lorem ipsum dolor sit amet, consectetur adipiscing elit.",
      "created_date": "2022-01-14T15:00:00.000Z",
      "updated_date": "2022-01-14T18:38:27.548Z",
      "tags": [
        "tag4",
        "tag4",
        "tag5",
        "tag4"
      ]
    },
    {
      "id": 16,
      "title": "Note 16",
      "content": "Lorem ipsum dolor sit amet, consectetur adipiscing elit.",
      "created_date": "2022-01-15T15:00:00.000Z",
      "updated_date": "2022-01-16T08:42:31.683Z",
      "tags": [
        "tag4"
      ]
    },
    {
      "id": 17,
      "title": "Note 17",
      "content": "Lorem ipsum dolor sit amet, consectetur adipiscing elit.",
      "created_date": "2022-01-16T15:00:00.000Z",
      "updated_date": "2022-01-17T05:10:54.033Z",
      "tags": []
    },
    {
      "id": 18,
      "title": "Note 18",
      "content": "Lorem ipsum dolor sit amet, consectetur adipiscing elit.",
      "created_date": "2022-01-17T15:00:00.000Z",
      "updated_date": "2022-01-17T16:20:12.883Z",
      "tags": [
        "tag1"
      ]
    },
    {
      "id": 19,
      "title": "Note 19",
      "content": "Lorem ipsum dolor sit amet, consectetur adipiscing elit.",
      "created_date": "2022-01-18T15:00:00.000Z",
      "updated_date": "2022-01-19T05:48:40.331Z",
      "tags": [
        "tag2",
        "tag1",
        "tag5"
      ]
    },
    {
      "id": 20,
      "title": "Note 20",
      "content": "Lorem ipsum dolor sit amet, consectetur adipiscing elit.",
      "created_date": "2022-01-19T15:00:00.000Z",
      "updated_date": "2022-01-19T20:35:20.953Z",
      "tags": []
    },
    {
      "id": 21,
      "title": "Note 21",
      "content": "Lorem ipsum dolor sit amet, consectetur adipiscing elit.",
      "created_date": "2022-01-20T15:00:00.000Z",
      "updated_date": "2022-01-21T12:47:19.147Z",
      "tags": [
        "tag4",
        "tag1",
        "tag5"
      ]
    },
    {
      "id": 22,
      "title": "Note 22",
      "content": "Lorem ipsum dolor sit amet, consectetur adipiscing elit.",
      "created_date": "2022-01-21T15:00:00.000Z",
      "updated_date": "2022-01-21T17:59:55.899Z",
      "tags": [
        "tag1"
      ]
    },
    {
      "id": 23,
      "title": "Note 23",
      "content": "Lorem ipsum dolor sit amet, consectetur adipiscing elit.",
      "created_date": "2022-01-22T15:00:00.000Z",
      "updated_date": "2022-01-23T14:07:28.777Z",
      "tags": [
        "tag3",
        "tag5",
        "tag4",
        "tag3"
      ]
    },
    {
      "id": 24,
      "title": "Note 24",
      "content": "Lorem ipsum dolor sit amet, consectetur adipiscing elit.",
      "created_date": "2022-01-23T15:00:00.000Z",
      "updated_date": "2022-01-23T17:04:04.494Z",
      "tags": [
        "tag5",
        "tag5",
        "tag2"
      ]
    },
    {
      "id": 25,
      "title": "Note 25",
      "content": "Lorem ipsum dolor sit amet, consectetur adipiscing elit.",
      "created_date": "2022-01-24T15:00:00.000Z",
      "updated_date": "2022-01-24T22:22:22.815Z",
      "tags": [
        "tag5",
        "tag4"
      ]
    },
    {
      "id": 26,
      "title": "Note 26",
      "content": "Lorem ipsum dolor sit amet, consectetur adipiscing elit.",
      "created_date": "2022-01-25T15:00:00.000Z",
      "updated_date": "2022-01-26T12:41:26.474Z",
      "tags": [
        "tag2",
        "tag1",
        "tag1"
      ]
    },
    {
      "id": 27,
      "title": "Note 27",
      "content": "Lorem ipsum dolor sit amet, consectetur adipiscing elit.",
      "created_date": "2022-01-26T15:00:00.000Z",
      "updated_date": "2022-01-26T20:52:31.862Z",
      "tags": [
        "tag5"
      ]
    },
    {
      "id": 28,
      "title": "Note 28",
      "content": "Lorem ipsum dolor sit amet, consectetur adipiscing elit.",
      "created_date": "2022-01-27T15:00:00.000Z",
      "updated_date": "2022-01-28T13:06:44.210Z",
      "tags": [
        "tag3",
        "tag2"
      ]
    },
    {
      "id": 29,
      "title": "Note 29",
      "content": "Lorem ipsum dolor sit amet, consectetur adipiscing elit.",
      "created_date": "2022-01-28T15:00:00.000Z",
      "updated_date": "2022-01-29T13:41:57.076Z",
      "tags": [
        "tag5",
        "tag2",
        "tag3",
        "tag4",
        "tag1"
      ]
    },
    {
      "id": 30,
      "title": "Note 30",
      "content": "Lorem ipsum dolor sit amet, consectetur adipiscing elit.",
      "created_date": "2022-01-29T15:00:00.000Z",
      "updated_date": "2022-01-29T19:15:27.602Z",
      "tags": []
    },
    {
      "id": 31,
      "title": "Note 31",
      "content": "Lorem ipsum dolor sit amet, consectetur adipiscing elit.",
      "created_date": "2022-01-30T15:00:00.000Z",
      "updated_date": "2022-01-31T10:35:28.116Z",
      "tags": []
    },
    {
      "id": 32,
      "title": "Note 32",
      "content": "Lorem ipsum dolor sit amet, consectetur adipiscing elit.",
      "created_date": "2022-01-31T15:00:00.000Z",
      "updated_date": "2022-01-31T15:12:33.654Z",
      "tags": [
        "tag5"
      ]
    },
    {
      "id": 33,
      "title": "Note 33",
      "content": "Lorem ipsum dolor sit amet, consectetur adipiscing elit.",
      "created_date": "2022-02-01T15:00:00.000Z",
      "updated_date": "2022-02-02T03:52:32.270Z",
      "tags": [
        "tag4",
        "tag2",
        "tag2"
      ]
    },
    {
      "id": 34,
      "title": "Note 34",
      "content": "Lorem ipsum dolor sit amet, consectetur adipiscing elit.",
      "created_date": "2022-02-02T15:00:00.000Z",
      "updated_date": "2022-02-02T15:32:44.205Z",
      "tags": [
        "tag1",
        "tag5",
        "tag1",
        "tag2"
      ]
    },
    {
      "id": 35,
      "title": "Note 35",
      "content": "Lorem ipsum dolor sit amet, consectetur adipiscing elit.",
      "created_date": "2022-02-03T15:00:00.000Z",
      "updated_date": "2022-02-03T21:39:31.185Z",
      "tags": [
        "tag2",
        "tag4",
        "tag1"
      ]
    },
    {
      "id": 36,
      "title": "Note 36",
      "content": "Lorem ipsum dolor sit amet, consectetur adipiscing elit.",
      "created_date": "2022-02-04T15:00:00.000Z",
      "updated_date": "2022-02-05T02:54:45.806Z",
      "tags": [
        "tag3",
        "tag2"
      ]
    },
    {
      "id": 37,
      "title": "Note 37",
      "content": "Lorem ipsum dolor sit amet, consectetur adipiscing elit.",
      "created_date": "2022-02-05T15:00:00.000Z",
      "updated_date": "2022-02-06T01:07:28.057Z",
      "tags": [
        "tag4",
        "tag2"
      ]
    },
    {
      "id": 38,
      "title": "Note 38",
      "content": "Lorem ipsum dolor sit amet, consectetur adipiscing elit.",
      "created_date": "2022-02-06T15:00:00.000Z",
      "updated_date": "2022-02-07T10:10:26.653Z",
      "tags": []
    },
    {
      "id": 39,
      "title": "Note 39",
      "content": "Lorem ipsum dolor sit amet, consectetur adipiscing elit.",
      "created_date": "2022-02-07T15:00:00.000Z",
      "updated_date": "2022-02-08T07:34:38.455Z",
      "tags": [
        "tag3",
        "tag2"
      ]
    },
    {
      "id": 40,
      "title": "Note 40",
      "content": "Lorem ipsum dolor sit amet, consectetur adipiscing elit.",
      "created_date": "2022-02-08T15:00:00.000Z",
      "updated_date": "2022-02-09T05:55:55.564Z",
      "tags": [
        "tag2",
        "tag2"
      ]
    },
    {
      "id": 41,
      "title": "Note 41",
      "content": "Lorem ipsum dolor sit amet, consectetur adipiscing elit.",
      "created_date": "2022-02-09T15:00:00.000Z",
      "updated_date": "2022-02-09T20:02:14.861Z",
      "tags": [
        "tag3",
        "tag4",
        "tag3",
        "tag5",
        "tag2"
      ]
    },
    {
      "id": 42,
      "title": "Note 42",
      "content": "Lorem ipsum dolor sit amet, consectetur adipiscing elit.",
      "created_date": "2022-02-10T15:00:00.000Z",
      "updated_date": "2022-02-10T16:20:26.170Z",
      "tags": [
        "tag2",
        "tag4",
        "tag2",
        "tag4",
        "tag1"
      ]
    },
    {
      "id": 43,
      "title": "Note 43",
      "content": "Lorem ipsum dolor sit amet, consectetur adipiscing elit.",
      "created_date": "2022-02-11T15:00:00.000Z",
      "updated_date": "2022-02-12T01:06:15.377Z",
      "tags": []
    },
    {
      "id": 44,
      "title": "Note 44",
      "content": "Lorem ipsum dolor sit amet, consectetur adipiscing elit.",
      "created_date": "2022-02-12T15:00:00.000Z",
      "updated_date": "2022-02-13T14:47:02.883Z",
      "tags": [
        "tag3",
        "tag5"
      ]
    },
    {
      "id": 45,
      "title": "Note 45",
      "content": "Lorem ipsum dolor sit amet, consectetur adipiscing elit.",
      "created_date": "2022-02-13T15:00:00.000Z",
      "updated_date": "2022-02-14T00:45:49.388Z",
      "tags": [
        "tag2"
      ]
    },
    {
      "id": 46,
      "title": "Note 46",
      "content": "Lorem ipsum dolor sit amet, consectetur adipiscing elit.",
      "created_date": "2022-02-14T15:00:00.000Z",
      "updated_date": "2022-02-14T21:47:48.206Z",
      "tags": [
        "tag2",
        "tag1",
        "tag4"
      ]
    },
    {
      "id": 47,
      "title": "Note 47",
      "content": "Lorem ipsum dolor sit amet, consectetur adipiscing elit.",
      "created_date": "2022-02-15T15:00:00.000Z",
      "updated_date": "2022-02-16T07:23:00.535Z",
      "tags": []
    },
    {
      "id": 48,
      "title": "Note 48",
      "content": "Lorem ipsum dolor sit amet, consectetur adipiscing elit.",
      "created_date": "2022-02-16T15:00:00.000Z",
      "updated_date": "2022-02-17T03:24:27.499Z",
      "tags": [
        "tag4",
        "tag5",
        "tag3",
        "tag4"
      ]
    },
    {
      "id": 49,
      "title": "Note 49",
      "content": "Lorem ipsum dolor sit amet, consectetur adipiscing elit.",
      "created_date": "2022-02-17T15:00:00.000Z",
      "updated_date": "2022-02-18T06:51:00.287Z",
      "tags": [
        "tag1"
      ]
    },
    {
      "id": 50,
      "title": "Note 50",
      "content": "Lorem ipsum dolor sit amet, consectetur adipiscing elit.",
      "created_date": "2022-02-18T15:00:00.000Z",
      "updated_date": "2022-02-19T12:56:16.522Z",
      "tags": []
    }
  ]
}